{
    "name": "MUSC 81C",
    "title": "Global Popular Music",
    "description": "This cultural study of global popular musics explores musical sounds, practices, and discourse via an examination of the development of the category world music. It explores how music and mass media engage broader issues around globalization, ethnic, national, and transnational identities; popular resistance; censorship; and cultural hegemony.",
    "pre_req_data": {
        "conditions": {
            "restricted_to_majors": "",
            "erlw": false,
            "lower_credits_limit": 0,
            "upper_credits_limit": 500
        },
        "text": "",
        "courses": [
            []
        ]
    },
    "class_notes": "NULL",
    "career": "Undergraduate",
    "gen_ed_code": "ER",
    "type": "Lecture",
    "credits": "5",
    "quarters_offered": [
        "fall"
    ],
    "quarterly_info": {
        "fall": {
            "total_seats": 375,
            "filled seats": 101,
            "priority": "very low"
        }
    }
}