{
    "name": "THEA 185",
    "title": "Senior Seminar",
    "description": "A required seminar for majors involving readings and discussions of important texts in dance, design, and drama.",
    "pre_req_data": {
        "conditions": {
            "restricted_to_majors": "",
            "erlw": false,
            "lower_credits_limit": 0,
            "upper_credits_limit": 500
        },
        "text": "Prerequisite(s): satisfaction of the Entry Level Writing and Composition requirements; THEA 160.",
        "courses": [
            [
                "P    E L W"
            ],
            [
                "C"
            ],
            [
                "THEA 160"
            ]
        ]
    },
    "class_notes": "NULL",
    "career": "Undergraduate",
    "gen_ed_code": "NULL",
    "type": "Seminar",
    "credits": "5",
    "quarters_offered": [
        "fall"
    ],
    "quarterly_info": {
        "fall": {
            "total_seats": 0,
            "filled seats": 36,
            "priority": "unavailible"
        }
    }
}